qufia/__init__.py
qufia/client.py
qufia/models.py
qufia/spatial.py
qufia/trees.py
qufia-0.1.1.dist-info/METADATA
qufia-0.1.1.dist-info/WHEEL
qufia-0.1.1.dist-info/top_level.txt
qufia-0.1.1.dist-info/RECORD
